aiask/__init__.py
aiask/consts.py
aiask/index.py
aiask/openai.py
aiask/utils.py
ask/__init__.py
ask/consts.py
ask/index.py
ask/openai.py
ask/utils.py
aiask-1.0.0.dist-info/METADATA
aiask-1.0.0.dist-info/WHEEL
aiask-1.0.0.dist-info/entry_points.txt
aiask-1.0.0.dist-info/top_level.txt
aiask-1.0.0.dist-info/RECORD
